localcloud/Makefile
localcloud/__init__.py
localcloud/cli.py
localcloud/tests/test_command_line_argument_parsing.py
localcloud-0.0.1.dist-info/METADATA
localcloud-0.0.1.dist-info/WHEEL
localcloud-0.0.1.dist-info/entry_points.txt
localcloud-0.0.1.dist-info/licenses/LICENSE
localcloud-0.0.1.dist-info/RECORD
